xoryx/__init__.py
xoryx/cli.py
xoryx/release.sh
xoryx-0.0.2.dist-info/METADATA
xoryx-0.0.2.dist-info/WHEEL
xoryx-0.0.2.dist-info/entry_points.txt
xoryx-0.0.2.dist-info/RECORD
