Metadata-Version: 2.4
Name: xoryx
Version: 0.0.2
Summary: experimentation
Author-email: AG <oss@ashgw.me>
License-Expression: MIT
Classifier: Typing :: Typed
Requires-Python: ~=3.10
